bvx_env/__init__.py
bvx_env/values.py
bvx_env-0.0.1.dist-info/LICENSE
bvx_env-0.0.1.dist-info/METADATA
bvx_env-0.0.1.dist-info/WHEEL
bvx_env-0.0.1.dist-info/top_level.txt
bvx_env-0.0.1.dist-info/RECORD
